tab_analysis/__init__.py
tab_analysis/analysis.py
tab_analysis-0.2.0.dist-info/METADATA
tab_analysis-0.2.0.dist-info/WHEEL
tab_analysis-0.2.0.dist-info/top_level.txt
tab_analysis-0.2.0.dist-info/RECORD
