Metadata-Version: 2.1
Name: tab_analysis
Version: 0.2.0
Summary: TAB-analysis : A tool to analyse tabular and multi-dimensionnal structures
Home-page: https://github.com/loco-philippe/tab-analysis/blob/main/README.md
Author: Philippe Thomy
Author-email: philippe@loco-labs.io
Keywords: tabular data,open data,environmental data
Classifier: Development Status :: 5 - Production/Stable
Classifier: Intended Audience :: Developers
Classifier: Topic :: Software Development :: Build Tools
Classifier: License :: OSI Approved :: MIT License
Classifier: Programming Language :: Python :: 3
Requires-Python: >=3.9, <4
